drf_http_response/__init__.py
drf_http_response/main.py
drf_http_response-0.0.1.0.dist-info/LICENSE
drf_http_response-0.0.1.0.dist-info/METADATA
drf_http_response-0.0.1.0.dist-info/WHEEL
drf_http_response-0.0.1.0.dist-info/entry_points.txt
drf_http_response-0.0.1.0.dist-info/top_level.txt
drf_http_response-0.0.1.0.dist-info/RECORD
