Metadata-Version: 2.1
Name: drf-http-response
Version: 0.0.1.0
Summary: UNKNOWN
Home-page: https://github.com/raisulru/drf-http-response.git
Author: Raisul
Author-email: raisul@kutumbita.com
License: License :: OSI Approved :: MIT License
Platform: UNKNOWN
Classifier: Programming Language :: Python
Requires-Python: >=3.6
